ruamel_yaml_line_info/__init__.py
ruamel_yaml_line_info/constructor.py
ruamel_yaml_line_info/main.py
ruamel_yaml_line_info/py.typed
ruamel_yaml_line_info-0.1.4.dist-info/LICENSE
ruamel_yaml_line_info-0.1.4.dist-info/METADATA
ruamel_yaml_line_info-0.1.4.dist-info/WHEEL
ruamel_yaml_line_info-0.1.4.dist-info/RECORD
