Metadata-Version: 2.3
Name: ruamel_yaml_line_info
Version: 0.1.4
Summary: Line information for ruamel.yaml.
License: MIT
Author: Nils Homer
Author-email: <nilshomer@gmail.com>
Requires-Python: >=3.9.0,<4.0
Classifier: Development Status :: 3 - Alpha
Classifier: License :: OSI Approved :: MIT License
Classifier: Programming Language :: Python :: 3
Classifier: Programming Language :: Python :: 3.9
Classifier: Programming Language :: Python :: 3.10
Classifier: Programming Language :: Python :: 3.11
Classifier: Programming Language :: Python :: 3.12
Classifier: Programming Language :: Python :: 3.13
Requires-Dist: ruamel-yaml (>=0.18.10,<0.19.0)
Project-URL: Bug Tracker, https://github.com/nh13/ruamel_yaml_line_info/issues
Project-URL: Documentation, https://github.com/nh13/ruamel_yaml_line_info
Project-URL: Homepage, https://github.com/nh13/ruamel_yaml_line_info
Project-URL: Repository, https://github.com/nh13/ruamel_yaml_line_info
